ycf/__init__.py
ycf/consts.py
ycf/main.py
ycf-0.0.1.dist-info/LICENSE
ycf-0.0.1.dist-info/METADATA
ycf-0.0.1.dist-info/WHEEL
ycf-0.0.1.dist-info/entry_points.txt
ycf-0.0.1.dist-info/top_level.txt
ycf-0.0.1.dist-info/RECORD
