Metadata-Version: 2.1
Name: ycf
Version: 0.0.1
Summary: A script to help solve problems
Author: UMadd
Project-URL: Homepage, https://github.com/UltraMadd/yourcodeforce
Project-URL: Bug Tracker, https://github.com/UltraMadd/yourcodeforce/issues
Classifier: Programming Language :: Python :: 3
Classifier: License :: OSI Approved :: MIT License
Classifier: Operating System :: OS Independent
Requires-Python: >=3.7
License-File: LICENSE
